qanalytics_python/__init__.py
qanalytics_python/qanalytics.py
qanalytics_python/test_qanalytics.py
qanalytics_python-1.0.1.dist-info/LICENSE.rst
qanalytics_python-1.0.1.dist-info/METADATA
qanalytics_python-1.0.1.dist-info/WHEEL
qanalytics_python-1.0.1.dist-info/entry_points.txt
qanalytics_python-1.0.1.dist-info/top_level.txt
qanalytics_python-1.0.1.dist-info/RECORD
