Metadata-Version: 2.1
Name: qanalytics-python
Version: 1.0.1
Summary: Library to consume qanalytics API services (https://www.qanalytics.cl)
Home-page: https://github.com/Eitol/qanalytics_python
Author: Hector Oliveros
Author-email: hector.oliveros.leon@gmail.com
License: MIT
Platform: UNKNOWN
Classifier: License :: OSI Approved :: MIT License
Classifier: Programming Language :: Python :: 3
Classifier: Programming Language :: Python :: 3.7
Requires-Dist: pytz
Requires-Dist: requests
Requires-Dist: urllib3
